mapz/__init__.py
mapz/mapz.py
mapz/methods/__init__.py
mapz/methods/copy.py
mapz/methods/get.py
mapz/methods/map.py
mapz/methods/merge.py
mapz/methods/set.py
mapz/methods/splitkey.py
mapz/methods/traverse.py
mapz/methods/update.py
mapz/modifiers/__init__.py
mapz/modifiers/case.py
mapz/modifiers/flatten.py
mapz/modifiers/mapping.py
mapz/modifiers/table.py
mapz/tests/__init__.py
mapz/tests/debug.py
mapz/tests/methods/test_copy.py
mapz/tests/methods/test_get.py
mapz/tests/methods/test_map.py
mapz/tests/methods/test_merge.py
mapz/tests/methods/test_set.py
mapz/tests/methods/test_splitkey.py
mapz/tests/methods/test_traverse.py
mapz/tests/methods/test_update.py
mapz/tests/modifiers/test_case.py
mapz/tests/modifiers/test_flatten.py
mapz/tests/modifiers/test_mapping.py
mapz/tests/modifiers/test_table.py
mapz/tests/test_mapz.py
mapz-1.1.28.dist-info/WHEEL
mapz-1.1.28.dist-info/METADATA
mapz-1.1.28.dist-info/RECORD
