Metadata-Version: 2.1
Name: mapz
Version: 1.1.28
Summary: Extension of dict features
Home-page: https://github.com/ilexconf/mapz
License: MIT
Keywords: map,dict,mapping,interface
Author: vduseev
Author-email: vagiz@duseev.com
Maintainer: vduseev
Maintainer-email: vagiz@duseev.com
Requires-Python: >=3.8,<4.0
Classifier: License :: OSI Approved :: MIT License
Classifier: Programming Language :: Python :: 3
Classifier: Programming Language :: Python :: 3.8
Classifier: Programming Language :: Python :: 3.9
Project-URL: Repository, https://github.com/ilexconf/mapz
